Opt4Deck/__init__.py
Opt4Deck/adjoint.py
Opt4Deck/bfgs.py
Opt4Deck/genetic.py
Opt4Deck/simplex.py
opt4deck-0.1.0.dist-info/METADATA
opt4deck-0.1.0.dist-info/WHEEL
opt4deck-0.1.0.dist-info/top_level.txt
opt4deck-0.1.0.dist-info/RECORD
