Metadata-Version: 2.4
Name: Opt4Deck
Version: 0.1.0
Summary: Opt4Deck optimization toolkit (simplex, bfgs, genetic, adjoint)
Requires-Python: >=3.6
Requires-Dist: numpy
